
{
  "Weapons": {

    "1H Swords": [
      {
        "Name": "Dagger",
        "Equipment Type ID": 0,
        "Unique Equipment ID": 0,
        "Physical Attack": 1,
        "Magical Attack": 0,
        "Physical Hit %": 5,
        "Magical Hit %": 0,
        "Critical Hit %": 0,
        "Critical Damage Multiplier": 0.0,
        "HP": 0,
        "MP": 0,
        "Physical Armour": 0,
        "Magical Armour": 0,
        "Evasion %": 0,
        "Movespeed": 0,
        "Magic Resist %": 0
      },
      {
        "Name": "Hand",
        "Equipment Type ID": 1,
        "Unique Equipment ID": 1,
        "Physical Attack": 1,
        "Magical Attack": 0,
        "Physical Hit %": 0,
        "Magical Hit %": 0,
        "Critical Hit %": 0,
        "Critical Damage Multiplier": 0.0,
        "HP": 0,
        "MP": 0,
        "Physical Armour": 0,
        "Magical Armour": 0,
        "Evasion %": 0,
        "Movespeed": 0,
        "Magic Resist %": 0
      }
    ],
    "2H Swords": [
      {
        "Name": "GreatSword",
        "Equipment Type ID": 2,
        "Unique Equipment ID": 2,
        "Physical Attack": 3,
        "Magical Attack": 0,
        "Physical Hit %": 5,
        "Magical Hit %": 0,
        "Critical Hit %": 0,
        "Critical Damage Multiplier": 0.0,
        "HP": 0,
        "MP": 0,
        "Physical Armour": 0,
        "Magical Armour": 0,
        "Evasion %": 0,
        "Movespeed": 0,
        "Magic Resist %": 0
      }
    ],
    "Axes": [
      {
        "Name": "Greataxe",
        "Equipment Type ID": 3,
        "Unique Equipment ID": 3,
        "Physical Attack": 4,
        "Magical Attack": 0,
        "Physical Hit %": 0,
        "Magical Hit %": 0,
        "Critical Hit %": 0,
        "Critical Damage Multiplier": 0.0,
        "HP": 0,
        "MP": 0,
        "Physical Armour": 0,
        "Magical Armour": 0,
        "Evasion %": 0,
        "Movespeed": 0,
        "Magic Resist %": 0
      }
    ],
    "Bows": [
      {
        "Name": "Bow",
        "Equipment Type ID": 4,
        "Unique Equipment ID": 4,
        "Physical Attack": 0,
        "Magical Attack": 0,
        "Physical Hit %": 10,
        "Magical Hit %": 0,
        "Critical Hit %": 0,
        "Critical Damage Multiplier": 0.0,
        "HP": 0,
        "MP": 0,
        "Physical Armour": 0,
        "Magical Armour": 0,
        "Evasion %": 0,
        "Movespeed": 0,
        "Magic Resist %": 0
      }
    ],
    "Staffs": [
      {
        "Name": "Old Rod",
        "Equipment Type ID": 5,
        "Unique Equipment ID": 5,
        "Physical Attack": 0,
        "Magical Attack": 3,
        "Physical Hit %": 0,
        "Magical Hit %": 5,
        "Critical Hit %": 0,
        "Critical Damage Multiplier": 0.0,
        "HP": 0,
        "MP": 0,
        "Physical Armour": 0,
        "Magical Armour": 0,
        "Evasion %": 0,
        "Movespeed": 0,
        "Magic Resist %": 0
      }
    ],
    "Books": [
      {
        "Name": "Magic Book",
        "Equipment Type ID": 6,
        "Unique Equipment ID": 6,
        "Physical Attack": 0,
        "Magical Attack": 1,
        "Physical Hit %": 0,
        "Magical Hit %": 15,
        "Critical Hit %": 0,
        "Critical Damage Multiplier": 0.0,
        "HP": 0,
        "MP": 0,
        "Physical Armour": 0,
        "Magical Armour": 0,
        "Evasion %": 0,
        "Movespeed": 0,
        "Magic Resist %": 0
      }
    ]
  },

  "Armour": {
    "Light Armour": [
      {
        "Name": "Tunic",
        "Equipment Type ID": 7,
        "Unique Equipment ID": 7,
        "Physical Attack": 0,
        "Magical Attack": 0,
        "Physical Hit %": 0,
        "Magical Hit %": 0,
        "Critical Hit %": 0,
        "Critical Damage Multiplier": 0,
        "HP": 0,
        "MP": 0,
        "Physical Armour": 1,
        "Magical Armour": 1,
        "Evasion %": 10,
        "Movespeed": 1,
        "Magic Resist %": 0
      }
    ],
 "Medium Armour": [
      {
        "Name": "Scale Mail",
        "Equipment Type ID": 8,
        "Unique Equipment ID": 8,
        "Physical Attack": 0,
        "Magical Attack": 0,
        "Physical Hit %": 0,
        "Magical Hit %": 0,
        "Critical Hit %": 0,
        "Critical Damage Multiplier": 0,
        "HP": 0,
        "MP": 0,
        "Physical Armour": 2,
        "Magical Armour": 2,
        "Evasion %": 5,
        "Movespeed": 0,
        "Magic Resist %": 5
      }
    ],
 "Heavy Armour": [
      {
        "Name": "Splint Armour",
        "Equipment Type ID": 9,
        "Unique Equipment ID": 9,
        "Physical Attack": 0,
        "Magical Attack": 0,
        "Physical Hit %": 0,
        "Magical Hit %": 0,
        "Critical Hit %": 0,
        "Critical Damage Multiplier": 0,
        "HP": 0,
        "MP": 0,
        "Physical Armour": 3,
        "Magical Armour": 3,
        "Evasion %": 0,
        "Movespeed": -1,
        "Magic Resist %": 10
      }
    ]
  },

  "Accessories": [

    {
      "Name": "Ring of movement",
      "Equipment Type ID": 10,
      "Unique Equipment ID": 10,
      "Physical Attack": 0,
      "Magical Attack": 0,
      "Physical Hit %": 0,
      "Magical Hit %": 0,
      "Critical Hit %": 0,
      "Critical Damage Multiplier": 0,
      "HP": 0,
      "MP": 0,
      "Physical Armour": 0,
      "Magical Armour": 0,
      "Evasion %": 0,
      "Movespeed": 1,
      "Magic Resist %": 0

    },
    {
      "Name": "Gem of evasion",
      "Equipment Type ID": 11,
      "Unique Equipment ID": 11,
      "Physical Attack": 0,
      "Magical Attack": 0,
      "Physical Hit %": 0,
      "Magical Hit %": 0,
      "Critical Hit %": 0,
      "Critical Damage Multiplier": 0,
      "HP": 0,
      "MP": 0,
      "Physical Armour": 0,
      "Magical Armour": 0,
      "Evasion %": 10,
      "Movespeed": 0,
      "Magic Resist %": 0
    },
    {
      "Name": "Ring of balance defense",
      "Equipment Type ID": 12,
      "Unique Equipment ID": 12,
      "Physical Attack": 0,
      "Magical Attack": 0,
      "Physical Hit %": 0,
      "Magical Hit %": 0,
      "Critical Hit %": 0,
      "Critical Damage Multiplier": 0,
      "HP": 0,
      "MP": 0,
      "Physical Armour": 2,
      "Magical Armour": 2,
      "Evasion %": 0,
      "Movespeed": 0,
      "Magic Resist %": 0
    },
    {
      "Name": "Ring of physical Focus",
      "Equipment Type ID": 13,
      "Unique Equipment ID": 13,
      "Physical Attack": 0,
      "Magical Attack": 0,
      "Physical Hit %": 10,
      "Magical Hit %": 0,
      "Critical Hit %": 0,
      "Critical Damage Multiplier": 0,
      "HP": 0,
      "MP": 0,
      "Physical Armour": 0,
      "Magical Armour": 0,
      "Evasion %": 0,
      "Movespeed": 0,
      "Magic Resist %": 0
    },
    {
      "Name": "Ring of physical defense",
      "Equipment Type ID": 14,
      "Unique Equipment ID": 14,
      "Physical Attack": 0,
      "Magical Attack": 0,
      "Physical Hit %": 0,
      "Magical Hit %": 0,
      "Critical Hit %": 0,
      "Critical Damage Multiplier": 0,
      "HP": 0,
      "MP": 0,
      "Physical Armour": 4,
      "Magical Armour": 0,
      "Evasion %": 0,
      "Movespeed": 0,
      "Magic Resist %": 0
    },
    {
      "Name": "Ring of Magic defense",
      "Equipment Type ID": 15,
      "Unique Equipment ID": 15,
      "Physical Attack": 0,
      "Magical Attack": 0,
      "Physical Hit %": 0,
      "Magical Hit %": 0,
      "Critical Hit %": 0,
      "Critical Damage Multiplier": 0,
      "HP": 0,
      "MP": 0,
      "Physical Armour": 0,
      "Magical Armour": 4,
      "Evasion %": 0,
      "Movespeed": 0,
      "Magic Resist %": 0
    },
    {
      "Name": "Gem of Critical Hit",
      "Equipment Type ID": 16,
      "Unique Equipment ID": 16,
      "Physical Attack": 0,
      "Magical Attack": 0,
      "Physical Hit %": 0,
      "Magical Hit %": 0,
      "Critical Hit %": 10,
      "Critical Damage Multiplier": 0,
      "HP": 0,
      "MP": 0,
      "Physical Armour": 0,
      "Magical Armour": 0,
      "Evasion %": 0,
      "Movespeed": 0,
      "Magic Resist %": 0
    },
    {
      "Name": "Gem of Magic Focus",
      "Equipment Type ID": 17,
      "Unique Equipment ID": 17,
      "Physical Attack": 0,
      "Magical Attack": 0,
      "Physical Hit %": 0,
      "Magical Hit %": 10,
      "Critical Hit %": 0,
      "Critical Damage Multiplier": 0,
      "HP": 0,
      "MP": 0,
      "Physical Armour": 0,
      "Magical Armour": 0,
      "Evasion %": 0,
      "Movespeed": 0,
      "Magic Resist %": 0
    },
    {
      "Name": "Gem of Critical Damage",
      "Equipment Type ID": 18,
      "Unique Equipment ID": 18,
      "Physical Attack": 0,
      "Magical Attack": 0,
      "Physical Hit %": 0,
      "Magical Hit %": 0,
      "Critical Hit %": 0,
      "Critical Damage Multiplier": 0.1,
      "HP": 0,
      "MP": 0,
      "Physical Armour": 0,
      "Magical Armour": 0,
      "Evasion %": 0,
      "Movespeed": 0,
      "Magic Resist %": 0
    }
  ]
}
